kdsm_centreon_api-0.2.3.dist-info/METADATA
kdsm_centreon_api-0.2.3.dist-info/WHEEL
kdsm_centreon_api-0.2.3.dist-info/entry_points.txt
kdsm_centreon_api/__init__.py
kdsm_centreon_api/api/__init__.py
kdsm_centreon_api/api/base_api.py
kdsm_centreon_api/api/centreon.py
kdsm_centreon_api/api/centreon_version.py
kdsm_centreon_api/api/host.py
kdsm_centreon_api/api/host_group.py
kdsm_centreon_api/api/host_template.py
kdsm_centreon_api/api/monitoring_server.py
kdsm_centreon_api/api/service.py
kdsm_centreon_api/api/service_group.py
kdsm_centreon_api/api/service_template.py
kdsm_centreon_api/api/sub_api.py
kdsm_centreon_api/api/utils.py
kdsm_centreon_api/logger.py
kdsm_centreon_api/models/__init__.py
kdsm_centreon_api/models/base.py
kdsm_centreon_api/models/host.py
kdsm_centreon_api/models/host_group.py
kdsm_centreon_api/models/host_template.py
kdsm_centreon_api/models/macro.py
kdsm_centreon_api/models/min_obj.py
kdsm_centreon_api/models/monitoring_server.py
kdsm_centreon_api/models/resource_status.py
kdsm_centreon_api/models/service.py
kdsm_centreon_api/models/service_group.py
kdsm_centreon_api/models/service_template.py
kdsm_centreon_api/models/snmp_version.py
kdsm_centreon_api-0.2.3.dist-info/RECORD
